{
    "sprint_id":  "S005",
    "snapshot_at":  "2026-03-29T21:49:08+08:00",
    "todo_ids":  [
                     "TODO-023",
                     "TODO-024",
                     "TODO-025",
                     "TODO-026",
                     "TODO-027",
                     "TODO-028"
                 ],
    "items":  [
                  {
                      "id":  "TODO-023",
                      "title":  "Completely remove hero and PERSONAL EDITION panel feel",
                      "status":  "implemented"
                  },
                  {
                      "id":  "TODO-024",
                      "title":  "Implement the AI Agent interaction layer from dynamic_effects.md",
                      "status":  "implemented"
                  },
                  {
                      "id":  "TODO-025",
                      "title":  "Implement travel and photography dynamic language from dynamic_effects.md",
                      "status":  "implemented"
                  },
                  {
                      "id":  "TODO-026",
                      "title":  "Implement music and finance dynamic language from dynamic_effects.md",
                      "status":  "implemented"
                  },
                  {
                      "id":  "TODO-027",
                      "title":  "Unify all dynamic effects into one restrained premium-artistic system",
                      "status":  "implemented"
                  },
                  {
                      "id":  "TODO-028",
                      "title":  "Document dynamic_effects compliance and user-override context",
                      "status":  "implemented"
                  }
              ]
}
