{
  "sprint_id": "S001",
  "evaluated_at": "2026-03-29T15:29:09+08:00",
  "evaluator": "evaluator",
  "result": "PASS",
  "summary": "S001 satisfies the contracted scope and verification metrics. Runtime, UI structure, responsive menu behavior, and safety checks passed. A missing favicon results in a non-blocking 404.",
  "results": [
    {
      "id": "CHECK-001",
      "status": "pass",
      "evidence": "Repository root contains `package.json`, `server.js`, `index.html`, `styles.css`, `main.js`, and `README.md`."
    },
    {
      "id": "CHECK-002",
      "status": "pass",
      "evidence": "A fresh local server start on port 4174 returned HTTP 200. The already running instance on port 4173 also returned HTTP 200."
    },
    {
      "id": "CHECK-003",
      "status": "pass",
      "evidence": "Verified visible single-page sections and anchors for about, projects, experience, and contact via source inspection and browser snapshot."
    },
    {
      "id": "CHECK-004",
      "status": "pass",
      "evidence": "At 390px viewport, the menu button is visible, the nav is hidden by default, and the menu expands when toggled."
    },
    {
      "id": "CHECK-005",
      "status": "pass",
      "evidence": "Verified semantic landmarks, heading hierarchy, skip link, keyboard-reachable links, and ARIA state on the mobile menu."
    },
    {
      "id": "CHECK-006",
      "status": "pass",
      "evidence": "`%SystemDrive%` remains outside the app entry points, is explicitly ignored in `.gitignore`, and retains the observed timestamp `2026-03-29T14:03:39.3465878+08:00`."
    }
  ],
  "checks": [
    {
      "id": "CHECK-001",
      "description": "A standard frontend project structure and dependency manifest exist in the repository root.",
      "type": "artifact"
    },
    {
      "id": "CHECK-002",
      "description": "The documented development command starts the project locally or is otherwise verifiably runnable.",
      "type": "runtime"
    },
    {
      "id": "CHECK-003",
      "description": "The homepage includes hero, about, projects, and contact coverage with usable navigation targets.",
      "type": "ui"
    },
    {
      "id": "CHECK-004",
      "description": "The layout remains usable on mobile and desktop widths without obvious blocking issues.",
      "type": "responsive"
    },
    {
      "id": "CHECK-005",
      "description": "Semantic structure, keyboard reachability, and readable contrast are addressed at a basic level.",
      "type": "accessibility"
    },
    {
      "id": "CHECK-006",
      "description": "The %SystemDrive% directory was left untouched during Sprint S001.",
      "type": "safety"
    }
  ]
}
